Example.v
module example(

    input clk,rst,
    input a,b,c,d,e,
    output reg f,f_clock,f_register
);

always @(*) //Cualquier cambio en las entradas a,b,c,d,e hará que se ejecute el bloque de código
begin
    f = (a & b) | (c & d) | e;
end

always @(posedge clk or posedge rst) //En cada flanco de subida del reloj o cuando se active el reset
begin
    if(rst) //Si el reset está activo
        f_clock <= 0; //Poner f a 0
    else
        f_clock <= (a & b) | (c & d) | e; //Sino, actualizar f con la nueva combinación de entradas
        f_register <= f_clock; //Actualizar el registro con el valor de f_clock
end

endmodule

Example_tb.v
module Example_tb;
reg clk, rst;
reg a, b, c, d, e;
wire f, f_clock,f_register;
// Instancia del módulo a probar
example uut (
    .clk(clk),
    .rst(rst),
    .a(a),     
    .b(b),
    .c(c),
    .d(d),
    .e(e),
    .f(f),
    .f_clock(f_clock),
    .f_register(f_register)
);

// Generación de reloj
always #5 clk = ~clk; // Cambia el estado del reloj cada 5 unidades

initial begin
    // Inicialización de señales
    rst = 0;
    #5;
    clk = 0;
    rst = 1; // Activar reset al inicio
    a = 0; b = 0; c = 0; d = 0; e = 0;

    // Desactivar reset después de un tiempo
    #10 rst = 0;

    // Cambiar las entradas para probar diferentes combinaciones
    #10 a = 1; b = 1; c = 0; d = 0; e = 0;
    #10 a = 0; b = 0; c = 1; d = 1; e = 0;
    #10 a = 0; b = 0; c = 0; d = 0; e = 1;
    #10 a = 1; b = 1; c = 1; d = 1; e = 1;
    #10 a = 1; b = 0; c = 1; d = 0; e = 1;
    #10 a = 0; b = 1; c = 0; d = 1; e = 0;
    #10 a = 1; b = 0; c = 0; d = 1; e = 0;
    repeat (5) 
    begin
    #10; // Esperar un poco más para observar el comportamiento
        a = $random%2; b = $random%2; c = $random%2; d = $random%2; e = $random%2; // Asignar valores aleatorios a las entradas
    end

    // Finalizar la simulación después de probar las combinaciones
    #10 $finish;
end

initial begin
    $dumpfile("Example_tb.vcd"); // Archivo para guardar la simulación
    $dumpvars(0, Example_tb); // Guardar todas las variables del testbench
    $monitor("At time %t: a=%b, b=%b, c=%b, d=%b, e=%b, f=%b", $time, a, b, c, d, e, f);
end

endmodule

Example_tb.vcd
$date
	Thu Feb 26 17:30:23 2026
$end
$version
	Icarus Verilog
$end
$timescale
	1s
$end
$scope module Example_tb $end
$var wire 1 ! f_register $end
$var wire 1 " f_clock $end
$var wire 1 # f $end
$var reg 1 $ a $end
$var reg 1 % b $end
$var reg 1 & c $end
$var reg 1 ' clk $end
$var reg 1 ( d $end
$var reg 1 ) e $end
$var reg 1 * rst $end
$scope module uut $end
$var wire 1 $ a $end
$var wire 1 % b $end
$var wire 1 & c $end
$var wire 1 ' clk $end
$var wire 1 ( d $end
$var wire 1 ) e $end
$var wire 1 * rst $end
$var reg 1 # f $end
$var reg 1 " f_clock $end
$var reg 1 ! f_register $end
$upscope $end
$upscope $end
$enddefinitions $end
$comment Show the parameter values. $end
$dumpall
$end
#0
$dumpvars
0*
x)
x(
x'
x&
x%
x$
x#
x"
x!
$end
#5
0"
0#
0)
0(
0&
0%
0$
1*
0'
#10
0!
1'
#15
0'
0*
#20
1'
#25
1#
0'
1%
1$
#30
1"
1'
#35
0'
1(
1&
0%
0$
#40
1!
1'
#45
0'
1)
0(
0&
#50
1'
#55
0'
1(
1&
1%
1$
#60
1'
#65
0'
0(
0%
#70
1'
#75
0#
0'
0)
1(
0&
1%
0$
#80
0"
1'
#85
0'
0%
1$
#90
0!
1'
#95
1#
0'
1)
1&
1%
0$
#100
1"
1'
#105
0'
0&
1$
#110
1!
1'
#115
0'
0(
1&
0$
#120
1'
#125
0'
1(
0&
#130
1'
#135
0#
0'
0)
0(
